bytealgebra/__init__.py
bytealgebra-1.1.1.dist-info/LICENCE.txt
bytealgebra-1.1.1.dist-info/METADATA
bytealgebra-1.1.1.dist-info/WHEEL
bytealgebra-1.1.1.dist-info/top_level.txt
bytealgebra-1.1.1.dist-info/RECORD
