Metadata-Version: 2.1
Name: bytealgebra
Version: 1.1.1
Summary: Algebraic Functions Package Built In Python Programming Languages
Home-page: https://github.com/boularbahsmail/bytealgebra
Author: Ismail Boularbah
Author-email: boularbahismail01@gmail.com
Classifier: Programming Language :: Python :: 3
Classifier: License :: OSI Approved :: MIT License
Classifier: Operating System :: OS Independent
License-File: LICENCE.txt
